{
  "dashboard": [
    {
      "id": "1",
      "name": "Cool",
      "keyword": "Cool Wallpaper",
      "image": "https://i.pinimg.com/originals/45/f3/59/45f359a8bf0a59173a4923f3fd32166e.jpg"
    },
    {
      "id": "2",
      "name": "Featured",
      "keyword": "Featured Wallpaper",
      "image": "http://img2.launcher.ksmobile.com/1215x1080/2016-12-08/275011_c62b76fd.jpg"
    },
    {
      "id": "3",
      "name": "Love",
      "keyword": "Love Wallpaper",
      "image": "http://img2.launcher.ksmobile.com/1215x1080/2016-12-08/275011_c62b76fd.jpg"
    },
    {
      "id": "4",
      "name": "Vehicle",
      "keyword": "Vehicle Wallpaper",
      "image": "xxxxx"
    },
    {
      "id": "5",
      "name": "Landscape",
      "keyword": "Landscape Wallpaper",
      "image": "xxxxx"
    },
    {
      "id": "6",
      "name": "Design",
      "keyword": "Design Wallpaper",
      "image": "xxxxx"
    },
    {
      "id": "6.1",
      "name": "Girl",
      "keyword": "Girl Wallpaper",
      "image": "xxxxx"
    },
    {
      "id": "7",
      "name": "Abstract",
      "keyword": "Abstract Wallpaper",
      "image": "xxxxx"
    },
    {
      "id": "8",
      "name": "Space",
      "keyword": "Space Wallpaper",
      "image": "xxxxx"
    },
    {
      "id": "9",
      "name": "Animal",
      "keyword": "Animal Wallpaper",
      "image": "xxxxx"
    },
    {
      "id": "9",
      "name": "Text",
      "keyword": "Text Wallpaper",
      "image": "xxxxx"
    },
    {
      "id": "10",
      "name": "Mountain",
      "keyword": "Mountain Wallpaper",
      "image": "xxxxx"
    },
    {
      "id": "11",
      "name": "Blue",
      "keyword": "Blue Wallpaper",
      "image": "xxxxx"
    },
    {
      "id": "12",
      "name": "Sunset",
      "keyword": "Sunset Wallpaper",
      "image": "xxxxx"
    },
    {
      "id": "13",
      "name": "Tree",
      "keyword": "Trees Wallpaper",
      "image": "xxxxx"
    },
    {
      "id": "14",
      "name": "Water",
      "keyword": "Water Wallpaper",
      "image": "xxxxx"
    },
    {
      "id": "15",
      "name": "Natural",
      "keyword": "Natural Wallpaper",
      "image": "xxxxx"
    },
    {
      "id": "16",
      "name": "Sea",
      "keyword": "Sea Wallpaper",
      "image": "xxxxx"
    },
    {
      "id": "17",
      "name": "Food",
      "keyword": "Food Wallpaper",
      "image": "xxxxx"
    },
    {
      "id": "18",
      "name": "Snow",
      "keyword": "Snow Wallpaper",
      "image": "xxxxx"
    },
    {
      "id": "19",
      "name": "Flower",
      "keyword": "Flower Wallpaper",
      "image": "xxxxx"
    },
    {
      "id": "20",
      "name": "Entertainment",
      "keyword": "Entertainment Wallpaper",
      "image": "xxxxx"
    },
    {
      "id": "21",
      "name": "Sport",
      "keyword": "Sport Wallpaper",
      "image": "xxxxx"
    },
    {
      "id": "22",
      "name": "Clouds",
      "keyword": "Clouds Wallpaper",
      "image": "xxxxx"
    },
    {
      "id": "23",
      "name": "Festival",
      "keyword": "Festival Wallpaper",
      "image": "xxxxx"
    },
    {
      "id": "24",
      "name": "Other",
      "keyword": "Other Wallpaper",
      "image": "xxxxx"
    }
  ],
  "appdata": {
    "version": "1.0",
    "name": "3 wallpaper",
    "link": "xxxx-app-link"
  },
  "message": "Sucess",
  "code": 200
}